GeoPatch/__init__.py
geopatch-1.3.2.dist-info/licenses/LICENSE.txt
geopatch-1.3.2.dist-info/METADATA
geopatch-1.3.2.dist-info/WHEEL
geopatch-1.3.2.dist-info/top_level.txt
geopatch-1.3.2.dist-info/RECORD
