Metadata-Version: 2.4
Name: GeoPatch
Version: 1.3.2
Summary: GeoPatch generates patches from remote sensing data and shapefiles for semantic segmentation and object detection with YOLO-format annotations
Home-page: https://github.com/Hejarshahabi/GeoPatch
Author: Hejar Shahabi
Author-email: hejarshahabi@gmail.com
License: MIT
Keywords: Machine Learning,Remote Sensing,Deep Learning,Object Detection,YOLO,Shapefile,GeoTIFF
Classifier: Development Status :: 5 - Production/Stable
Classifier: Intended Audience :: Science/Research
Classifier: Operating System :: Microsoft :: Windows :: Windows 10
Classifier: Operating System :: Microsoft :: Windows :: Windows 11
Classifier: Operating System :: POSIX :: Linux
Classifier: License :: OSI Approved :: MIT License
Classifier: Programming Language :: Python :: 3
Classifier: Programming Language :: Python :: 3.8
Classifier: Programming Language :: Python :: 3.9
Classifier: Programming Language :: Python :: 3.10
Classifier: Programming Language :: Python :: 3.11
Classifier: Programming Language :: Python :: 3.12
Requires-Python: >=3.8
License-File: LICENSE.txt
Requires-Dist: numpy>=1.21.0
Requires-Dist: pandas>=1.3.0
Requires-Dist: matplotlib>=3.4.0
Requires-Dist: scikit-learn>=0.24.0
Requires-Dist: rasterio>=1.2.0
Requires-Dist: geopandas>=0.10.0
Requires-Dist: shapely>=1.8.0
Requires-Dist: tqdm>=4.60.0
Requires-Dist: scikit-image>=0.18.0
Requires-Dist: GDAL>=3.0.0
Dynamic: author
Dynamic: author-email
Dynamic: classifier
Dynamic: description
Dynamic: description-content-type
Dynamic: home-page
Dynamic: keywords
Dynamic: license
Dynamic: license-file
Dynamic: requires-dist
Dynamic: requires-python
Dynamic: summary
